saved_instance/__init__.py
saved_instance/base_storage.py
saved_instance/cli.py
saved_instance/factory.py
saved_instance/rich_storage.py
saved_instance/secure_storage.py
saved_instance/simple_storage.py
saved_instance/utils.py
saved_instance/cmd/__init__.py
saved_instance/cmd/cmd.py
saved_instance/config/__init__.py
saved_instance/config/config_data.py
saved_instance/db/__init__.py
saved_instance/db/base_repo.py
saved_instance/db/shelve_repo.py
saved_instance/db/sqllite_repo.py
saved_instance-0.2.0.dist-info/METADATA
saved_instance-0.2.0.dist-info/WHEEL
saved_instance-0.2.0.dist-info/entry_points.txt
saved_instance-0.2.0.dist-info/licenses/LICENSE
saved_instance-0.2.0.dist-info/RECORD
